odoo/addons/stock_mass_scrap/README.rst
odoo/addons/stock_mass_scrap/__init__.py
odoo/addons/stock_mass_scrap/__manifest__.py
odoo/addons/stock_mass_scrap/data/ir_actions_server.xml
odoo/addons/stock_mass_scrap/i18n/fr.po
odoo/addons/stock_mass_scrap/i18n/stock_mass_scrap.pot
odoo/addons/stock_mass_scrap/models/__init__.py
odoo/addons/stock_mass_scrap/models/stock_scrap.py
odoo/addons/stock_mass_scrap/readme/CONTRIBUTORS.rst
odoo/addons/stock_mass_scrap/readme/DESCRIPTION.rst
odoo/addons/stock_mass_scrap/security/ir.model.access.csv
odoo/addons/stock_mass_scrap/static/description/icon.png
odoo/addons/stock_mass_scrap/static/description/index.html
odoo/addons/stock_mass_scrap/tests/__init__.py
odoo/addons/stock_mass_scrap/tests/test_mass_scrap.py
odoo/addons/stock_mass_scrap/wizard/__init__.py
odoo/addons/stock_mass_scrap/wizard/mass_scrap.py
odoo/addons/stock_mass_scrap/wizard/mass_scrap.xml
odoo14_addon_stock_mass_scrap-14.0.1.0.1.dist-info/METADATA
odoo14_addon_stock_mass_scrap-14.0.1.0.1.dist-info/WHEEL
odoo14_addon_stock_mass_scrap-14.0.1.0.1.dist-info/top_level.txt
odoo14_addon_stock_mass_scrap-14.0.1.0.1.dist-info/RECORD
